Workbook

Sheet sheet1
A1: S.No | B1: USERNAME | C1: Caption | D1: Followers | E1: Hashtags | F1: Hashtag_count | G1: Time since posted | H1: Likes | I1: Like_rate | J1: Hours_Posted
A2: 24 | B2: astrokpj | C2: Was invited to speak at the annual Machine Learning conference on the role of Artificial Intelligence in big physics experiments such as LIGO. Much potential for astrophysics to collaborate with Tech giants Google, IBM and other large experiments at CERN. | D2: 3448 | E2: #artificialintelligence #machinelearning#bigdata #supercomputer #science#astrophysics #astronomy #einstein#relativity #theoryofrelativity #georgiatech#computerscience #blackhole #universe#cosmos | F2: =LEN(E2)-LEN(SUBSTITUTE(E2,"#","")) -> 15 | G2: 24 hours | H2: 349 | I2: =(H2/D2)*100 -> 10.12181 | J2: =VALUE(LEFT(G2,SEARCH(" ",G2)-1)) -> 24
A3: 17 | B3: gsmusicgroupllc | C3: gsmusicgroupllc#Repost @savageland32with @get_repost #SkrappdaGawd New Music on ALL Platforms | D3: 226 | E3: #youtube #applemusic #itunes#soundcloud #spinrilla #spotify #bigdata#blockchain #dontbandwagonlater | F3: =LEN(E3)-LEN(SUBSTITUTE(E3,"#","")) -> 9 | G3: 2 hours | H3: 350 | I3: =(H3/D3)*100 -> 154.86726 | J3: =VALUE(LEFT(G3,SEARCH(" ",G3)-1)) -> 2
A4: 24 | B4: lb3enterprises | C4: We’re only paid to move dirt once. It’s not just about excavating but placing it too. If fills aren’t properly planned for and executed, it can lead to moving material a second time which you don’t get paid for. That’s where good managers and operators who envision the final product are key. We’re hiring operators and grade checkers - send us an email at jobs@lb3enterprises.com to apply! | D4: 2039 | E4: #heavyequipment #underconstruction#dozer #realestate #bluecollar #D10#ibuildamerica #earthmover #caterpillar#demolition #mining #dumptruck #builtforit#truck #trucks #underconstruction#engineering #ironworker #construction#developer #dirt #constructionworker#safety #madeinamerica #excavator#civilengineering #quarry #Americanmade#development #operator | F4: =LEN(E4)-LEN(SUBSTITUTE(E4,"#","")) -> 30 | G4: 3 hours | H4: 351 | I4: =(H4/D4)*100 -> 17.214321 | J4: =VALUE(LEFT(G4,SEARCH(" ",G4)-1)) -> 3
A5: 26 | B5: superdatascience | C5: Live Population in Manhattan (hour-by-hour). Gif credit: @citrusvanilla . | D5: 966 | E5: #datascience #data #tech #technology#future #machinelearning #ai#visualizations #dataisbeautiful | F5: =LEN(E5)-LEN(SUBSTITUTE(E5,"#","")) -> 9 | G5: 5 hours | H5: 352 | I5: =(H5/D5)*100 -> 36.438923 | J5: =VALUE(LEFT(G5,SEARCH(" ",G5)-1)) -> 5
A6: 20 | B6: orcan_intel | C6: Global warming visualised. | D6: 2277 | E6: #data #bigdata #datavisualization#datascience #artificialintelligence | F6: =LEN(E6)-LEN(SUBSTITUTE(E6,"#","")) -> 5 | G6: 4 hours | H6: 353 | I6: =(H6/D6)*100 -> 15.502855 | J6: =VALUE(LEFT(G6,SEARCH(" ",G6)-1)) -> 4
A7: 5 | B7: theminest_ | C7: Instructions unclear... 🤔. Started building two speakers and ended up with two mining rigs 🤦‍♂️ | D7: 1618 | E7: #theminest #miningrig #gpumining#bitcoinmining #bitcoin #bitcoinmemes#cryptolife #cryptomemes #cryptomining#ethereum #litecoin #cryptonews #altcoins#hodl #hodlgang #investinyourself#blockchain #crypto #miningfarm#ethereummining #litecoinmining#bitcointrading #bitcoinexchange #bitcoins#coinbase | F7: =LEN(E7)-LEN(SUBSTITUTE(E7,"#","")) -> 25 | G7: 20 hours | H7: 354 | I7: =(H7/D7)*100 -> 21.878863 | J7: =VALUE(LEFT(G7,SEARCH(" ",G7)-1)) -> 20
A8: 1 | B8: mikequindazzi | C8: Who are #DataScientist and what do they do? >> @MikeQuindazzi >> #MachineLearning #AI #DataAnalytics #DataScienc #DataLake >> https://buff.ly/2kYmF0s | D8: 1600 | E8: #MachineLearning #AI #DataAnalytics #DataScienc #DataLake | F8: =LEN(E8)-LEN(SUBSTITUTE(E8,"#","")) -> 5 | G8: 11 hours | H8: 355 | I8: =(H8/D8)*100 -> 22.1875 | J8: =VALUE(LEFT(G8,SEARCH(" ",G8)-1)) -> 11
A9: 5 | B9: mikequindazzi | C9: 1 in 3 #Smartphones will ship w/ #MachineLearning and #ArtificialIntelligence at the chipset level by 2020 >> @MikeQuindazzi >> #IoT #AI 2018 Report >> https://buff.ly/2HV0VAQ | D9: 1600 | E9: #MachineLearning #artificialintelligence#AI #IoT | F9: =LEN(E9)-LEN(SUBSTITUTE(E9,"#","")) -> 4 | G9: 14 hours | H9: 356 | I9: =(H9/D9)*100 -> 22.25 | J9: =VALUE(LEFT(G9,SEARCH(" ",G9)-1)) -> 14
A10: 7 | B10: rare.planet | C10: Our most selling hand painted kettle!! Order this beautiful kettle now!! . | D10: 2573 | E10: #rareplanet #shopatrareplanet #India#indiangood #kolkata #calcutta#handpainted #homedecor #gifts#terracotta #kettles #product #likesforfollow #like4like #instalike#like4likeback #likes4tags | F10: =LEN(E10)-LEN(SUBSTITUTE(E10,"#","")) -> 17 | G10: 2 hours | H10: 357 | I10: =(H10/D10)*100 -> 13.874854 | J10: =VALUE(LEFT(G10,SEARCH(" ",G10)-1)) -> 2
A11: 25 | B11: palmariusdev | C11: Obtén tu tienda en línea ahora. | D11: 741 | E11: #marketing #programming#development #desarrollo #webdesign#diseñoweb #frontend #backend #apps#app #mobileapps #aplicaciones #españa#panama #argentina #chile #uruguay#digitalmarketing #socialmedia#ecommerce #tiendaonline #design#startup #emprender #website #paginaweb#followme #work #business #empresa | F11: =LEN(E11)-LEN(SUBSTITUTE(E11,"#","")) -> 30 | G11: 3 hours | H11: 358 | I11: =(H11/D11)*100 -> 48.31309 | J11: =VALUE(LEFT(G11,SEARCH(" ",G11)-1)) -> 3
A12: 15 | B12: artificialintelligence.a.i | C12: Tag him who promised to help you but he doesn't 😒.😂 | D12: 533 | E12: #artificialintelligence #ai#machinelearning#deeplearning #algorithm #algorithms #cs#ml #blockchain #sopia#robots #project#aiproject#tag#it#boats#artificialintelligenceai #github #data #python #R #coding#programming #coder #programmer | F12: =LEN(E12)-LEN(SUBSTITUTE(E12,"#","")) -> 25 | G12: 11 hours | H12: 94 | I12: =(H12/D12)*100 -> 17.636023 | J12: =VALUE(LEFT(G12,SEARCH(" ",G12)-1)) -> 11
A13: 21 | B13: bitpainting | C13: At 12 Noon EST today, BitPainting will be releasing a new work of rare #blockchain art! From Picasso to Van Gogh, build your iconic art collection on the #ethereum network! | D13: 835 | E13: #blockchain #ethereum | F13: =LEN(E13)-LEN(SUBSTITUTE(E13,"#","")) -> 2 | G13: 2 hours | H13: 93 | I13: =(H13/D13)*100 -> 11.137725 | J13: =VALUE(LEFT(G13,SEARCH(" ",G13)-1)) -> 2
... A33: 11 | B33: hollympeck | C33: Still on set. 🙃 Can't tell you what it's for! | D33: 273 | E33: #artificialintelligence | F33: =LEN(E33)-LEN(SUBSTITUTE(E33,"#","")) -> 1 | G33: 2 hours | H33: 41 | I33: =(H33/D33)*100 -> 15.018315 | J33: =VALUE(LEFT(G33,SEARCH(" ",G33)-1)) -> 2
A34: 17 | B34: remi_ole | D34: 2175 | E34: #entrepreneur #entrepreneurial#entrepreneurmindset #fametags#entrepreneurship #entrepreneurslife#entrepreneurs #entrepreneurquotes#entrepreneurlifestyle #business#businessowner #ceo #boss #top #high#rich #success #hustle #luxury #millionaire#billionaire #lifegoals #motivational #goals#grind #ambition #startup #mindset#achive #hardwork | F34: =LEN(E34)-LEN(SUBSTITUTE(E34,"#","")) -> 30 | G34: 2 hours | H34: 41 | I34: =(H34/D34)*100 -> 1.8850575 | J34: =VALUE(LEFT(G34,SEARCH(" ",G34)-1)) -> 2
A35: 19 | B35: greg_turner44 | C35: Join the international community of forex trading and change your financial situation with knowledge on binary and forex trading Grow your investment and smile tomorrow. With such an investment of $500 your guaranteed of making $4835 back as profit in a time frame of 14 days. This is no scam or joke, totally legitimate. DM me now for more info on my trading platform. | D35: 1003 | E35: #forex #rich #wealth #millionaire #invest#wallstreet #business #entrepreneurs#startup #startups #startuplife #technology#tech #digital #computer #gadget #gadgets#geek #geeks #media #newslol #books#reading #read #entrepreneurship#businessman #reader #marketingdigital#goodreads #seo | F35: =LEN(E35)-LEN(SUBSTITUTE(E35,"#","")) -> 30 | G35: 2 hours | H35: 40 | I35: =(H35/D35)*100 -> 3.9880359 | J35: =VALUE(LEFT(G35,SEARCH(" ",G35)-1)) -> 2
A36: 9 | B36: philosophercoin | C36: Isn't it funny to think that Bitcoin uses Artificial Scarcity to tackle inflation? - Follow me for more. | D36: 279 | E36: #Bitcoin #Cryptocurrency#Ethereum #stockmarket #currencytrading#digitalmarketing #litecoin #Currency #ico#token #mining #BitcoinExchange#Blockchain #money #community #crypto#CryptoExchange #fiat #forex #altcoin#stocks #profit #investor #investment#trader#forextrader #nyse #broker #forexnews#forexanalysis | F36: =LEN(E36)-LEN(SUBSTITUTE(E36,"#","")) -> 30 | G36: 2 hours | H36: 37 | I36: =(H36/D36)*100 -> 13.261649 | J36: =VALUE(LEFT(G36,SEARCH(" ",G36)-1)) -> 2
A37: 6 | B37: iamjaradwright | C37: Go get yours now! . | D37: 740 | E37: #product #moderndesign #concept#designing #designs #interiorarchitecture#designers #prototype #instadesign#menswear #ootdmen #lookoftheday#snobshots #streetwear #urbanfashion#fashiondiaries #menwithstreetstyle#menstyle #fashionkiller #fashiongram#weloveatl #whyiloveatl #discoveratl#atlantacollective #igersatlanta#atlantasnaps #dji #djimavic #dronestagram#drones | F37: =LEN(E37)-LEN(SUBSTITUTE(E37,"#","")) -> 30 | G37: 2 hours | H37: 35 | I37: =(H37/D37)*100 -> 4.7297297 | J37: =VALUE(LEFT(G37,SEARCH(" ",G37)-1)) -> 2
A38: 7 | B38: lenovoworkstations | C38: Check it out – we’re walking across the 🌎’s first #3DPrintedbridge w/ smart sensors for real-time data in #VR with #ThinkRevolutionist@MX3DBridge #NXTBLD . | D38: 259 | E38: .#Tech #virtualreality #IoT #Machinelearning | F38: =LEN(E38)-LEN(SUBSTITUTE(E38,"#","")) -> 4 | G38: 3 hours | H38: 35 | I38: =(H38/D38)*100 -> 13.513514 | J38: =VALUE(LEFT(G38,SEARCH(" ",G38)-1)) -> 3
A39: 24 | B39: writtorg | C39: "It is this perfect accuracy, this lack of play, of variety, that makes the machine-made article so lifeless." | D39: 2691 | E39: #newread #whattoread #summerreads#nowreading #readingislife #bookworm#booknerds #writt #writtorg #wellread#bookreco #bookrecommendations#whatareyoureading #igbooks #igreads#bookclub #bookalicious #classicliterature#classicbooks #bestquotes #quotes#goodreads #bookaddict #bookoftheday#quoteoftheday #machinelearning#machines #creativity #art | F39: =LEN(E39)-LEN(SUBSTITUTE(E39,"#","")) -> 29 | G39: 4 hours | H39: 34 | I39: =(H39/D39)*100 -> 1.2634708 | J39: =VALUE(LEFT(G39,SEARCH(" ",G39)-1)) -> 4
A40: 22 | B40: pazrahn | C40: The Peter McKinnon - Created this ridiculous mini cinema rig from left over camera gear. The inspiration came from YouTubers like Peter McKinnon so I named this rig after him. Perfect for filming coffee to making sweet low walking shots and epic selfie videos. | D40: 361 | E40: #pmbrollchallenge #Canon#Atomos #Panasonic #Movo #MovoVXR10#Sony #CanonLegriaMiniX #LegriaMiniX#Cine #Luts #Canada #SmallRig #product#moderndesign #concept #designing#designs #interiorarchitecture#magnumphotos #streetlife #documentary#exploreaustralia #australiagram#ilovesydney #canonphotos #canoneos | F40: =LEN(E40)-LEN(SUBSTITUTE(E40,"#","")) -> 27 | G40: 3 hours | H40: 33 | I40: =(H40/D40)*100 -> 9.1412742 | J40: =VALUE(LEFT(G40,SEARCH(" ",G40)-1)) -> 3
A41: 13 | B41: the_ios_developer | C41: 4K Ai | D41: 863 | E41: #developer #coding #programmer #javascript #programming #software #php#webdeveloper #computerscience #html #css #webdevelopment #java #coder #html5#webdev #backend #programmers #softwaredeveloper #softwareengineering #python#webdesign #frontend #development #css3 #wordpress #code #webdesigner #js | F41: =LEN(E41)-LEN(SUBSTITUTE(E41,"#","")) -> 29 | G41: 2 hours | H41: 32 | I41: =(H41/D41)*100 -> 3.7079954 | J41: =VALUE(LEFT(G41,SEARCH(" ",G41)-1)) -> 2
A42: 11 | B42: databowl | C42: Today we are featured in The Future CMO Magazine in @thetimes@raconteur_london Go get a copy! Read more here: https://www.raconteur.net/sponsored/how-to-use-machine-learning-the-right-way-tool-for-a-new-marketing-paradigm | D42: 149 | E42: #artificialintelligence #futurism#machinelearning #marketing#b2cmarketing #thetimes #thedrum#hubspot #leadgeneration | F42: =LEN(E42)-LEN(SUBSTITUTE(E42,"#","")) -> 9 | G42: 7 hours | H42: 31 | I42: =(H42/D42)*100 -> 20.805369 | J42: =VALUE(LEFT(G42,SEARCH(" ",G42)-1)) -> 7
A43: 14 | B43: entrancegmbh | C43: Greetings from #CEBIT2018#Pepper is getting ready for #afterwork#party #festival #tradefair maybe we get on #stage with #digitalism | D43: 122 | E43: #hannover #cebit#digitalisierung #entrancegmbh #wuppertal#startup #iot #AI #artificialintelligence | F43: =LEN(E43)-LEN(SUBSTITUTE(E43,"#","")) -> 9 | G43: 2 hours | H43: 31 | I43: =(H43/D43)*100 -> 25.409836 | J43: =VALUE(LEFT(G43,SEARCH(" ",G43)-1)) -> 2
A44: 17 | B44: illumensfragrance | C44: simple elegance from @mumzynotjess featuring Illumens ‘Poire 1796’ diffuser. We love seeing our products in your beautiful homes, thank you Jess | D44: 845 | E44: #repost #interiors#white #elegant #simple #minimal#poire1796 #scentyourhome#illumensfragrance #loveillumens#whiteblog #product #whiteinteriors #home | F44: =LEN(E44)-LEN(SUBSTITUTE(E44,"#","")) -> 14 | G44: 2 hours | H44: 31 | I44: =(H44/D44)*100 -> 3.6686391 | J44: =VALUE(LEFT(G44,SEARCH(" ",G44)-1)) -> 2
A45: 19 | B45: michaelgarza__ | C45: 328 S. Wetherly Drive, Beverly Hills, CA 90212. This beautiful new construction our team completed in early May 2018 was sold before the framing was even started!! I am kidding, but it sure felt that way! | D45: 614 | E45: #beverlyhills #realestate#losangelesrealestate #gc&management #standardoil #standardoilrealty#luxuryrealestate #luxurydesign#losangeles #designer #development#homes #interiordesign #hustle#luxurylifestyle | F45: =LEN(E45)-LEN(SUBSTITUTE(E45,"#","")) -> 15 | G45: 3 hours | H45: 31 | I45: =(H45/D45)*100 -> 5.0488599 | J45: =VALUE(LEFT(G45,SEARCH(" ",G45)-1)) -> 3
A46: 16 | B46: thebeautymindset | C46: Im limited edition 💁 -------------------------------📣 Donr forget to TURN ON notification ---- | D46: 151 | E46: thebeautymindset#businessman#quoteoftheday #businessowner#businesswoman #success #grind#motivation #motivational #lifestyle#happiness #entrepreneurs#entrepreneurlife #business #working #founder#startup #money #magazine #moneymaker#startuplife #successful #passion #inspiredaily#hardwork #hardworkpaysoff #desire | F46: =LEN(E46)-LEN(SUBSTITUTE(E46,"#","")) -> 26 | G46: 2 hours | H46: 31 | I46: =(H46/D46)*100 -> 20.529801 | J46: =VALUE(LEFT(G46,SEARCH(" ",G46)-1)) -> 2
... A49: 15 | B49: cryptocrackhead | C49: I officially spent the last of my tethers and available liquidity. All one can do now is be patient and remember why you bought Crypto in the first place. Mass adaption and bull run will follow shortly. Stay focused and blessed my fellow Cryptocrackhead's! Will be opening up our Telegram Group to the public soon, so stay tuned... the main event hasn't even begun yet. 😜🚀💰 | D49: 610 | E49: #cryptocrackhead#blockchain#cryptocurrency #crypto #decentralise#bitcoin #ethereum #ripple #dash#bitcoincash #monero #eos #cardano #tron#fiat #millionaire #trading #altcoins #money#future #biitcoinaire #gains #funny#currency #coinbase #freedom #binance#virtual #ai #coins | F49: =LEN(E49)-LEN(SUBSTITUTE(E49,"#","")) -> 30 | G49: 2 hours | H49: 30 | I49: =(H49/D49)*100 -> 4.9180328 | J49: =VALUE(LEFT(G49,SEARCH(" ",G49)-1)) -> 2
A50: 11 | B50: anandvanjape | D50: 460 | E50: #Designer #style #artist#brand #logo #monogram #corporate#identity #lifestyle #pure #luxury #product#posh #london #paris #milan #newyork#dubai #sydney #melbourne #mumbai#dublin #dubai #cosmetics #fashion #art#artdirector #creativity #creative #colour#abstract | F50: =LEN(E50)-LEN(SUBSTITUTE(E50,"#","")) -> 31 | G50: 2 hours | H50: 29 | I50: =(H50/D50)*100 -> 6.3043478 | J50: =VALUE(LEFT(G50,SEARCH(" ",G50)-1)) -> 2
A51: 10 | B51: brad_0611 | C51: Living in Texas is easy, even if your standards are high 😎💁‍♂️ // | D51: 1158 | E51: #frisco#dallas #dfw #texas #newconstruction#economy #development #landscaping#design #ivoteyes | F51: =LEN(E51)-LEN(SUBSTITUTE(E51,"#","")) -> 10 | G51: 2 hours | H51: 29 | I51: =(H51/D51)*100 -> 2.5043178 | J51: =VALUE(LEFT(G51,SEARCH(" ",G51)-1)) -> 2
A52: 21 | B52: eligible.api | C52: GG, you always have the best T-shirts! 🔥❄️💉 #codeblooded | D52: 285 | E52: #Eligible #EligibleAPI #HealthCare#HealthCareTech #HealthIT #engineering#Programming #Code #Software #API#HIPAA #AI #MachineLearning#DeepLearning #Tech #StartupLife#DataScience #security #Compliance | F52: =LEN(E52)-LEN(SUBSTITUTE(E52,"#","")) -> 19 | G52: 4 hours | H52: 29 | I52: =(H52/D52)*100 -> 10.175439 | J52: =VALUE(LEFT(G52,SEARCH(" ",G52)-1)) -> 4
A53: 14 | B53: magnodc | C53: Acción es la mejor arma 🌏🏰 | D53: 2014 | E53: #moneymaker #startup #entrepreneurlife#entrepreneurs #entrepreneurlifestyle#entrepreneurship #onlinemarketing#motivational #millionairemindset#successful #millionairelifestyle#businesswoman #inspiredaily#businessman #founder #businessowner#youngentrepreneur #startuplife #igersperu#discoverperu #sudamerica #ig_peru_#experienceperu #exploreperu #focalmarked #motivation #tbt #followme | F53: =LEN(E53)-LEN(SUBSTITUTE(E53,"#","")) -> 28 | G53: 2 hours | H53: 29 | I53: =(H53/D53)*100 -> 1.4399206 | J53: =VALUE(LEFT(G53,SEARCH(" ",G53)-1)) -> 2
A54: 18 | B54: ansonmccade | C54: Do you really need #blockchain? | D54: 2904 | E54: #blockchaintechnology #blockchains #tech#technology #IoT #InternetOfThings#Bitcoin #business #businessintelligence#BI #AI #ArtificialIntelligence #ML#MachineLearning #infographic #DL#DeepLearning #data #bigdata#datascience | F54: =LEN(E54)-LEN(SUBSTITUTE(E54,"#","")) -> 20 | G54: 3 hours | H54: 28 | I54: =(H54/D54)*100 -> 0.96418733 | J54: =VALUE(LEFT(G54,SEARCH(" ",G54)-1)) -> 3
A55: 12 | B55: mrproductionmiami | C55: “The picture that you took with your camera is the imagination you want to create with reality.”👍 💥Good weekend to everyone 😀 | D55: 140 | E55: #roamtheplanet #travelphotography#visualoflife #beachlife #dametraveler#artofvisuals #islandhopping#flashesofdelight #thecreative #product#moderndesign #concept #designing#designs #interiorarchitecture #designers#prototype #instadesign #designporn#innovation #igersmiami #miaexplore#miamiphotographer #ig_miami#roamflorida #lifestyle_miami #panasonic#lumix #panasoniclumix #gh5 | F55: =LEN(E55)-LEN(SUBSTITUTE(E55,"#","")) -> 30 | G55: 2 hours | H55: 28 | I55: =(H55/D55)*100 -> 20 | J55: =VALUE(LEFT(G55,SEARCH(" ",G55)-1)) -> 2
A56: 7 | B56: cris.nemeth | C56: All black & shiny ✨✨ | D56: 577 | E56: #allblackeverything #applewatch#applewatchseries3 #38mm #swarovski#pandora #weekendvibes #style #fashion#tech #startup | F56: =LEN(E56)-LEN(SUBSTITUTE(E56,"#","")) -> 11 | G56: 2 hours | H56: 27 | I56: =(H56/D56)*100 -> 4.6793761 | J56: =VALUE(LEFT(G56,SEARCH(" ",G56)-1)) -> 2
A57: 3 | B57: aitrading_official | C57: Alexander Barinov: 4 years as CFO in multinationals, over 10 years of experience as financial advisory in Deloitte & EY, 6 of them as a partner. Focused on strategic management, finance, legal, and compliance. Worked for the global corporations including publicly traded companies. 5 years experience in trading at NYSE and LSE exchanges. #whoiswho #aitrading #ai #aitradingteam#instateam #instapeople #ai #trading#artificialintelligence #crypto#cryptocurrency #blockchain #tradingforex#forex #fiatmoney #coins #machinelearning#userexperience #instamachinelearning#instabigdata #instamarketing#artificialintelligence #deeplearning#datascience #industry #marketing#bigdata #datascience #machinelearning#ml | D57: 255 | E57: #whoiswho #aitrading #ai #aitradingteam#instateam #instapeople #ai #trading#artificialintelligence #crypto#cryptocurrency #blockchain #tradingforex#forex #fiatmoney #coins #machinelearning#userexperience #instamachinelearning#instabigdata #instamarketing#artificialintelligence #deeplearning#datascience #industry #marketing#bigdata #datascience #machinelearning#ml | F57: =LEN(E57)-LEN(SUBSTITUTE(E57,"#","")) -> 30 | G57: 2 hours | H57: 25 | I57: =(H57/D57)*100 -> 9.8039216 | J57: =VALUE(LEFT(G57,SEARCH(" ",G57)-1)) -> 2
A58: 30 | B58: coding.is.life | C58: #Repost @wesabio Sometimes the truth hurts | | D58: 265 | E58: #Repost #Javascript #ReactJS #Ruby #GDPR #Graduation #Mobile#VueJS #JQuery #Developers #Programmers #JS #Gift #Dev #ArtificialIntelligence #MachineLearning #Linux#Humour #Humor #Fintech #API #Sysadmin #ML #WomenInTech #Ubuntu #Security#IIOT #Hackers #TechHumor | F58: =LEN(E58)-LEN(SUBSTITUTE(E58,"#","")) -> 29 | G58: 2 hours | H58: 25 | I58: =(H58/D58)*100 -> 9.4339623 | J58: =VALUE(LEFT(G58,SEARCH(" ",G58)-1)) -> 2
A59: 19 | B59: triatebr | C59: Imagine having access to the data of the air we breathe? | D59: 1766 | E59: #blockchain #tech #startups #projetos#linux #ethereum #programmer#InternetdasCoisas #smartcontract#internetofthings #technology #disruption#mobile #nodemcu #hyperledger #chain#programming #smartcontracts#hyperledgerfabric #artificialintelligence#iot #fintech #industry40 #cloud#mobilelegends #drones#personaldevelopment #healthy | F59: =LEN(E59)-LEN(SUBSTITUTE(E59,"#","")) -> 28 | G59: 4 hours | H59: 25 | I59: =(H59/D59)*100 -> 1.4156285 | J59: =VALUE(LEFT(G59,SEARCH(" ",G59)-1)) -> 4
A60: 22 | B60: _linda_smith567 | C60: Hello ......You could see the excitement in her face .....one of my client who just cash out and still willing to invest more.Dm me for your trading help | D60: 124 | E60: #любовь #gm #sme #smenigeria #profits#businessowners #businessplan#entrepreneurship #entrepreneur#blockchain #crypto #cointelegraph#bitcoinprice #mining #cryptocurrencies#bch #bitcoins #litecoin #investment#investor #stockmarket #stocks #getrich#makemoney #makemoneyonline#mentorship #mentoring #xrp #bitfinex#altcoins | F60: =LEN(E60)-LEN(SUBSTITUTE(E60,"#","")) -> 30 | G60: 2 hours | H60: 24 | I60: =(H60/D60)*100 -> 19.354839 | J60: =VALUE(LEFT(G60,SEARCH(" ",G60)-1)) -> 2
A61: 22 | B61: funnelaico | C61: Lead with the #AI advantage. | D61: 87 | E61: #AI #machinelearning #auto#realtors #tech#fitness #socialselling#artificialintelligence#local #sanantonio#realestate #socialmedia#business #sa#generator #car #innovation#cardealers#entrepreneurs #COO #app#sales #ML | F61: =LEN(E61)-LEN(SUBSTITUTE(E61,"#","")) -> 23 | G61: 4 hours | H61: 24 | I61: =(H61/D61)*100 -> 27.586207 | J61: =VALUE(LEFT(G61,SEARCH(" ",G61)-1)) -> 4
A62: 6 | B62: meganbloemsma | C62: Together with my colleague Valery we introduced potential partners to #Azure @spacesworks #zuidas. It's great to see there's such an interest in Data & AI, and a lot of fun to come up with new ways to apply it with these companies. 🤓 | D62: 258 | E62: #techtaster #datagirl#womanintech #technicalevangelist#technicalevangelism #datascientist#datascience #datagirl #ai#artificialintelligence #advancedanalytics#cognitiveservices #faceAPI #demo#everydaytechday #womeninmicrosoft#womenintech #luis #azureML#cognitiveservices #datainsights#microsoftpartner | F62: =LEN(E62)-LEN(SUBSTITUTE(E62,"#","")) -> 22 | G62: 2 hours | H62: 24 | I62: =(H62/D62)*100 -> 9.3023256 | J62: =VALUE(LEFT(G62,SEARCH(" ",G62)-1)) -> 2
A63: 23 | B63: monde_informatique | D63: 2455 | E63: monde_informatique#client #project#product #projectmanager | F63: =LEN(E63)-LEN(SUBSTITUTE(E63,"#","")) -> 4 | G63: 3 hours | H63: 24 | I63: =(H63/D63)*100 -> 0.97759674 | J63: =VALUE(LEFT(G63,SEARCH(" ",G63)-1)) -> 3
A64: 18 | B64: praveen_rangasubhe | C64: 😂😂 | D64: 49 | E64: #html #html5 #webdeveloper#websitedesign #htmlcss #web#development #developer #code#programming | F64: =LEN(E64)-LEN(SUBSTITUTE(E64,"#","")) -> 10 | G64: 3 hours | H64: 24 | I64: =(H64/D64)*100 -> 48.979592 | J64: =VALUE(LEFT(G64,SEARCH(" ",G64)-1)) -> 3
A65: 15 | B65: usccareercenter | C65: Today we’re hosting Career Services and Academic advising professionals from across @uscedu campus and international offices. Today’s topic is on “In the Age of Artificial Intelligence: the Next Generation of Career Services.” | D65: 1180 | E65: #AI #machinelearning #artificialintelligence #careerservices #studentlearning | F65: =LEN(E65)-LEN(SUBSTITUTE(E65,"#","")) -> 5 | G65: 2 hours | H65: 24 | I65: =(H65/D65)*100 -> 2.0338983 | J65: =VALUE(LEFT(G65,SEARCH(" ",G65)-1)) -> 2
A66: 2 | B66: drgorillapaints | C66: We all know where it’s going. We just have to #workresponsibly to postpone the date. This actually made into a business slide #deck .#mac #macintosh#sayhello #apple #stevejobs #ai #evolution#artificialintelligence #machinelearning#terminator #illbeback #technology#computerevolution #computerscience#sciencefiction#computersciencetosciencefiction#tomorrowstechnology #vr #ar #robot#robots #t2 #businessdeck #businessslides#illustration #sketches #drawing | D66: 880 | E66: #deck .#mac #macintosh#sayhello #apple #stevejobs #ai #evolution#artificialintelligence #machinelearning#terminator #illbeback #technology#computerevolution #computerscience#sciencefiction#computersciencetosciencefiction#tomorrowstechnology #vr #ar #robot#robots #t2 #businessdeck #businessslides#illustration #sketches #drawing | F66: =LEN(E66)-LEN(SUBSTITUTE(E66,"#","")) -> 28 | G66: 2 hours | H66: 23 | I66: =(H66/D66)*100 -> 2.6136364 | J66: =VALUE(LEFT(G66,SEARCH(" ",G66)-1)) -> 2
A67: 9 | B67: ethicsandai | C67: Having a great week at @ldntechweek exploring what's new in the world of technology and listening to what the speakers have to say. It's so great, (and interesting!), to see so many people with a passion and common insterest gather on one place to discuss our world's future, and how technology will play it's part. @techxlr8 | D67: 13 | E67: #LTW #London #TechXLR8 #Technology#AI #ArtificialIntelligence #MachineLearning#Data #Future #Ethics #HumanRights#WomenInTech #WomenInSTEM #OurWorld#LondonTechWeek #EthicalTech#EthicsAndAI | F67: =LEN(E67)-LEN(SUBSTITUTE(E67,"#","")) -> 17 | G67: 4 hours | H67: 22 | I67: =(H67/D67)*100 -> 169.23077 | J67: =VALUE(LEFT(G67,SEARCH(" ",G67)-1)) -> 4
A68: 27 | B68: ivarski | C68: Morning swim before the sun is up 🇮🇹☀️ | D68: 918 | E68: #livinginitaly #tuscanyitaly#summerinitaly🇮🇹 #startup #startuplife#artificialintelligence #algorithm#voicebiometrics #myvoiceai | F68: =LEN(E68)-LEN(SUBSTITUTE(E68,"#","")) -> 9 | G68: 2 hours | H68: 21 | I68: =(H68/D68)*100 -> 2.2875817 | J68: =VALUE(LEFT(G68,SEARCH(" ",G68)-1)) -> 2
A69: 23 | B69: siansocial | C69: Have a great weekend all! 💜💜💜 | D69: 1200 | E69: #weekend #chill #chilling #Summer#founder #startup #smallbusiness #smallbiz#contentmarketing #consulting | F69: =LEN(E69)-LEN(SUBSTITUTE(E69,"#","")) -> 10 | G69: 2 hours | H69: 21 | I69: =(H69/D69)*100 -> 1.75 | J69: =VALUE(LEFT(G69,SEARCH(" ",G69)-1)) -> 2
A70: 17 | B70: benasdzimidas | C70: 60% off Lux Light until Monday! Get your copy now @ bit.ly/getluxlight ⠀⠀⠀⠀ | D70: 179 | E70: #android #design #development#benasdzimidas #graphicdesign #launcher#customisation #material #flat #flatshadow#iconography #ui #ux #graphicdesigner#graphicdesign #photoshop #illustrator#adobe #color #vector #creative #follow#wallpaper #wallpapers #androidwallpaper#photography #minimal #architecture #text#sale | F70: =LEN(E70)-LEN(SUBSTITUTE(E70,"#","")) -> 30 | G70: 2 hours | H70: 20 | I70: =(H70/D70)*100 -> 11.173184 | J70: =VALUE(LEFT(G70,SEARCH(" ",G70)-1)) -> 2
A71: 25 | B71: kamalalshehabi | D71: 955 | E71: #qoute #success#motivation #entrepreneur #inspiration#startup #follow #read | F71: =LEN(E71)-LEN(SUBSTITUTE(E71,"#","")) -> 8 | G71: 2 hours | H71: 20 | I71: =(H71/D71)*100 -> 2.0942408 | J71: =VALUE(LEFT(G71,SEARCH(" ",G71)-1)) -> 2
A72: 18 | B72: mbnsolutions | C72: @pedrodoc82 and @michaely76 from MBN are working in London today. Great to be talking Data Science, Analytics, Technology with our clients. If you are looking for a new job, register with us - www.mbnsolutions.com/jobs | D72: 935 | E72: #machinelearning #artificialintelligence#blockchain #data #datascience #analytics#technology #london #hiring | F72: =LEN(E72)-LEN(SUBSTITUTE(E72,"#","")) -> 9 | G72: 4 hours | H72: 20 | I72: =(H72/D72)*100 -> 2.1390374 | J72: =VALUE(LEFT(G72,SEARCH(" ",G72)-1)) -> 4
A73: 26 | B73: onthetopsearch | C73: “No one buys things from Facebook.” “Instagram is a fad.” “Snapchat will soon be gone.” We didn’t buy into what traditional marketing agencies said and our clients have reaped the benefits. Now, traditional marketers are scrambling to learn what we have been doing for years.At On The Top Search, we don’t quit. Ever. We will go to exhaustive measures to ensure your experience with us has a positive ROI. If not, drop us. | D73: 1041 | E73: #digitalmarketing #machinelearning#entrepreneurship #businessminded#fourthofjuly | F73: =LEN(E73)-LEN(SUBSTITUTE(E73,"#","")) -> 5 | G73: 2 hours | H73: 20 | I73: =(H73/D73)*100 -> 1.9212296 | J73: =VALUE(LEFT(G73,SEARCH(" ",G73)-1)) -> 2
A74: 12 | B74: alpha_mentor_ | C74: Double TAP if you support this message & TAG who would love to motivate, empower and inspire! Follow 👉 @alpha_mentor_ 💡 Turn On Post Notifications To See New Posts. 💡 Share With Friends & Family | D74: 89 | E74: #mentoring #enterprenuership #grind#hustle #learn #education #startup#dreamwork #successquotes #build#empire #startuplife #businessowners#ambition #dreams #goals #lifegoals#goforit #nevergiveup #sucessmindset#businesswoman #businessman#businesslife #enterpreneurlifestyle#goodlife #motivated #enterpreneurmindset#millionairemindset | F74: =LEN(E74)-LEN(SUBSTITUTE(E74,"#","")) -> 28 | G74: 2 hours | H74: 19 | I74: =(H74/D74)*100 -> 21.348315 | J74: =VALUE(LEFT(G74,SEARCH(" ",G74)-1)) -> 2
A75: 12 | B75: neondistrictrpg | C75: Character feature - The Architect - who wants to #cosplay this guy!? 🙋🏻‍♀️ Concept art for a high-level, tank-y character class. | D75: 12 | E75: #cosplay#gamerguy #conceptart #cryptocurrency#handdrawn #digitalart #rpg #pcgamer#comingsoon #videogames #cryptogame#cyberpunk #armor #scifi #dystopia#games #blockchain #instagamer#neondistrict #degen #themainspring | F75: =LEN(E75)-LEN(SUBSTITUTE(E75,"#","")) -> 21 | G75: 2 hours | H75: 19 | I75: =(H75/D75)*100 -> 158.33333 | J75: =VALUE(LEFT(G75,SEARCH(" ",G75)-1)) -> 2
A76: 18 | B76: shine_my_idol | C76: Life is all about the next step💎 | D76: 371 | E76: #Entrepreneur#Business#Entrepreneurship#WontStop#Mindset#Success#Hustle#Freedom#BusinessOwner#OnlineBusiness#Coaching#Ambition#Inspire#ThinkBig#Startup#HardWork#Businessman#BeYourOwnBoss#SmallBusiness#Believe#Motivate#Mentor or #mentoring#Givingback#InternetBusiness#Successe | F76: =LEN(E76)-LEN(SUBSTITUTE(E76,"#","")) -> 26 | G76: 2 hours | H76: 19 | I76: =(H76/D76)*100 -> 5.1212938 | J76: =VALUE(LEFT(G76,SEARCH(" ",G76)-1)) -> 2
A77: 25 | B77: xotivtechnologies | C77: The Various Aspects of Artificial Intelligence we should keep in mind. #Artificial #Intelligence is the new era for technologies to grow our business and provide powerful services. | D77: 334 | E77: #Artificial #Intelligence #AI #MachineLearning #DeepLearning #Robotics #BigData #Dataviz #Analytics #SMM #IoT #Sensors #Xotiv #NLP #datascience #graph #graphanalysis #visualisation #image #analytics #imageanalytics #coder #software #business #Development | F77: =LEN(E77)-LEN(SUBSTITUTE(E77,"#","")) -> 25 | G77: 2 hours | H77: 19 | I77: =(H77/D77)*100 -> 5.6886228 | J77: =VALUE(LEFT(G77,SEARCH(" ",G77)-1)) -> 2
A78: 6 | B78: be.masterly | C78: Cyber attacks are more frequent every day and they can affect businesses of all sizes from all around the world. In the #bemasterly course, you’ll learn first-hand how to plan ahead and prevent potential attacks, how to detect an attack and importantly how to respond from a legal, public, internal and technical perspective https://buff.ly/2EeE0JS | D78: 1231 | E78: #edtech #learning#educationtechnology #tech #learnnewskills #onlinelearning #teach #study #lifelonglearning #bigdata #chatbot #digitalliteracy #entrepreneurship #entrepreneur #startup #startupaus #studying #entrepreneur #machinelearning #coach #tech#techstartup #blockchain #videocourse #analytics | F78: =LEN(E78)-LEN(SUBSTITUTE(E78,"#","")) -> 25 | G78: 3 hours | H78: 18 | I78: =(H78/D78)*100 -> 1.4622258 | J78: =VALUE(LEFT(G78,SEARCH(" ",G78)-1)) -> 3
A79: 10 | B79: diworksolucionesdeti | C79: The Internet of Things : A Very Short Story [#Infographic] #Wearable #Sensors #MachineLearning#IoT #BigData #DigitalTransformation#futureofwork #marketing #analytics#bigdata #Cloud #Blogging#ContentMarketing #DigitalMarketing ht: #BigData #MachineLearning #AI #IoT#infograp | D79: 450 | E79: [#Infographic] #Wearable #Sensors #MachineLearning#IoT #BigData #DigitalTransformation#futureofwork #marketing #analytics#bigdata #Cloud #Blogging#ContentMarketing #DigitalMarketing ht: #BigData #MachineLearning #AI #IoT#infograp | F79: =LEN(E79)-LEN(SUBSTITUTE(E79,"#","")) -> 20 | G79: 7 hours | H79: 18 | I79: =(H79/D79)*100 -> 4 | J79: =VALUE(LEFT(G79,SEARCH(" ",G79)-1)) -> 7
A80: 23 | B80: litebit.eu | C80: As a safety measure for your account, we ask you to enable 2FA security before any withdrawal or sell can be made. Note: withdrawals and sell orders can only be made 24 hours after setting up 2FA. For questions please contact our support channels 👨‍🔧 #LiteBit | D80: 193 | E80: #bitcoin #litecoin #blockchain#cryptocurrency #ripple #coins #tech#litebiteu #ethereum #reddcoin #verge #Litebit | F80: =LEN(E80)-LEN(SUBSTITUTE(E80,"#","")) -> 12 | G80: 2 hours | H80: 18 | I80: =(H80/D80)*100 -> 9.3264249 | J80: =VALUE(LEFT(G80,SEARCH(" ",G80)-1)) -> 2
A81: 25 | B81: big.data.hush | C81: Recently, computer scientists have been working on teaching machines to do a wider range of tasks around the house. In a new paper spearheaded by MIT's Computer Science and Artificial Intelligence Laboratory (CSAIL) and the University of Toronto, researchers demonstrate "VirtualHome," a system that can simulate detailed household tasks and then have artificial "agents" execute them, opening up the possibility of one day teaching robots to do such tasks. | D81: 530 | E81: #bitcoin #ethereum #BTC#fun #Profit #success #business#motivation #rich #economy#cryptocurrency #news #fact #news#quotes #quote #Google #robot #laugh#ArtificialIntelligence #MachineLearning#DeepLearning #AI #Technology #Robotics#News #Facts #Fact #Startup #Joke | F81: =LEN(E81)-LEN(SUBSTITUTE(E81,"#","")) -> 30 | G81: 2 hours | H81: 17 | I81: =(H81/D81)*100 -> 3.2075472 | J81: =VALUE(LEFT(G81,SEARCH(" ",G81)-1)) -> 2
A82: 21 | B82: opensourcedworkplace | D82: 348 | E82: #HR #workplace#officedesign #iot #bigdata #office#facilitymanagement #technology#realestate #tech #work #futureofwork#computerscience #officespace #facility#smartcity #artificialintelligence#opensource #softwareengineer#workplacedesign #smartcities#autonomous #singularity #iiot #CEO#csuite #employeeengagement#employeeexperience #CHRO#businessowner | F82: =LEN(E82)-LEN(SUBSTITUTE(E82,"#","")) -> 30 | G82: 4 hours | H82: 17 | I82: =(H82/D82)*100 -> 4.8850575 | J82: =VALUE(LEFT(G82,SEARCH(" ",G82)-1)) -> 4
A83: 12 | B83: inmemovement | D83: 1196 | E83: #INME #inmemovement#indianeedsmoreentrepreneurs#entrepreneurindia #entrepreneur#entrepreneurlife #entrepreneurship#bigthings #life #startups #business#startup #movement #knowledge#development #india #join | F83: =LEN(E83)-LEN(SUBSTITUTE(E83,"#","")) -> 17 | G83: 2 hours | H83: 16 | I83: =(H83/D83)*100 -> 1.3377926 | J83: =VALUE(LEFT(G83,SEARCH(" ",G83)-1)) -> 2
A84: 11 | B84: interplayofficial | C84: On the auspicious occasion of Eid, Interplay would like to wish you abundance, happiness, and lots of blessings. | D84: 66 | E84: #Interplay #EidMubarak #EidulFitr #Eid#Eidblessings #EidBliss#EidSaeed #Eid2018#DigitalMarketingAgency #SocialMedia#digitalmarketing #onlinemarketing#startup #creativeagency #growdigitally | F84: =LEN(E84)-LEN(SUBSTITUTE(E84,"#","")) -> 15 | G84: 3 hours | H84: 16 | I84: =(H84/D84)*100 -> 24.242424 | J84: =VALUE(LEFT(G84,SEARCH(" ",G84)-1)) -> 3
A85: 13 | B85: interwall | C85: CEBIT 2018: Europas Business-Festival für Innovation und Digitalisierung | D85: 118 | E85: #cebit18 #cebit #hannover #cebit2018#ceyouinabit #messehannover#hannovermesse #artificialintelligence#künstlicheintelligenz #informatik | F85: =LEN(E85)-LEN(SUBSTITUTE(E85,"#","")) -> 10 | G85: 2 hours | H85: 16 | I85: =(H85/D85)*100 -> 13.559322 | J85: =VALUE(LEFT(G85,SEARCH(" ",G85)-1)) -> 2
A86: 29 | B86: roland.busch | C86: Very impressed by the ingenuity of our PhD students. Great to meet you at @Siemens Young Researcher Forum in Nuremberg! You really drive | D86: 145 | E86: #Innovation in #Connectivity #EdgeDevices#EnergyStorage #EnergyDistribution #DataAnalytics #ArtificialIntelligence | F86: =LEN(E86)-LEN(SUBSTITUTE(E86,"#","")) -> 7 | G86: 2 hours | H86: 16 | I86: =(H86/D86)*100 -> 11.034483 | J86: =VALUE(LEFT(G86,SEARCH(" ",G86)-1)) -> 2
A87: 18 | B87: applewantnews | C87: Apple is looking beyond just TV with a push for animated feature film. Based on appleinsider (ai), the company is in negotiations with Oscar-nominated Irish studio, Cartoon Saloon, known for movie like 'The Secret of Kells' and more. Apple intents to handle distributions and preparing to launch high-budget TV slate sometimes in 2019, as soon as March. | D87: 91 | E87: #tvOS #Apple #AppleNews #AppleDesign#WWDC #WWDC18 #WWDC2018#applewatch #iphone #tv #2018 #ios12#interesting #concepts #iphonese#iphonese2 #product #notconfirmed#budget #unknown #cartoon #high#instagram | F87: =LEN(E87)-LEN(SUBSTITUTE(E87,"#","")) -> 23 | G87: 3 hours | H87: 14 | I87: =(H87/D87)*100 -> 15.384615 | J87: =VALUE(LEFT(G87,SEARCH(" ",G87)-1)) -> 3
A88: 14 | B88: blocsidesports | C88: #WorldCup is here and BlocSide is bringing back our favorite game just for football #fans around the world! #linkinbio . Play new rounds EVERYDAY and win #mvp#tokens! | D88: 894 | E88: #sports #football #footy #footballfans#footballplayer #soccer #soccerfans#soccerlife #fifa #fifa18 #fifaworldcup#blockchain #spottheball #gametime#fifagame #playtowin #play #eyeontheprize#tech #technology | F88: =LEN(E88)-LEN(SUBSTITUTE(E88,"#","")) -> 20 | G88: 2 hours | H88: 14 | I88: =(H88/D88)*100 -> 1.5659955 | J88: =VALUE(LEFT(G88,SEARCH(" ",G88)-1)) -> 2
A89: 20 | B89: iotatokennews | C89: Bartosz Kusmierz, Research Scientist at #IOTA Foundation,spoke at the #Wrocław #Blockchain Meetup yesterday about IOTA! | D89: 1168 | E89: #IOTA #Wroclaw #Blockchain | F89: =LEN(E89)-LEN(SUBSTITUTE(E89,"#","")) -> 3 | G89: 2 hours | H89: 13 | I89: =(H89/D89)*100 -> 1.1130137 | J89: =VALUE(LEFT(G89,SEARCH(" ",G89)-1)) -> 2
A90: 15 | B90: caseyjmcclure | C90: Picked up this roubo bookstand from my buddy over at @holdfastcreations and it serves its purpose really well. Got a new book to use it for too, which is also pretty good. #theverticaldietfeeds my body, but I still have to feed my mind. Cyber is a beautiful battlefield. | D90: 106 | E90: #cybersecurity #programmer #development#nerd #mentalfitness | F90: =LEN(E90)-LEN(SUBSTITUTE(E90,"#","")) -> 5 | G90: 2 hours | H90: 12 | I90: =(H90/D90)*100 -> 11.320755 | J90: =VALUE(LEFT(G90,SEARCH(" ",G90)-1)) -> 2
A91: 10 | B91: vaultcolombia | C91: Nike Air 270. Pocas unidades disponibles. Información DM📥 | D91: 246 | E91: #gear #mensfashion #womenfashion #lids#product #newfamily #import #export#borondo #power #powerlifting #snapback#luxury #holiday #custom #crossfit #bogota#bogotagym #bogotacolombia #bogotadc#starkgym #fitlife #candy #sponsor#followforfollow #follow4follow | F91: =LEN(E91)-LEN(SUBSTITUTE(E91,"#","")) -> 26 | G91: 2 hours | H91: 12 | I91: =(H91/D91)*100 -> 4.8780488 | J91: =VALUE(LEFT(G91,SEARCH(" ",G91)-1)) -> 2
A92: 8 | B92: flornasweets | C92: Its a unicorn kind of day 💖. | D92: 181 | E92: #cookie #cookier #baking #icing #flooding#creativeprocess #treats #sweet #sets#product #cute #yummy #flornasweets#bakery #smallbusiness #colourful #bbq | F92: =LEN(E92)-LEN(SUBSTITUTE(E92,"#","")) -> 17 | G92: 2 hours | H92: 11 | I92: =(H92/D92)*100 -> 6.0773481 | J92: =VALUE(LEFT(G92,SEARCH(" ",G92)-1)) -> 2
A93: 28 | B93: mikequindazzi | C93: 8.5 billion more #smartphones by 2021 will help democratize #AI around the world >> @Qualcomm via @MikeQuindazzi >> | D93: 4496 | E93: #DeepLearning #MachineLearning#ArtificialIntelligence #IoT #BigData#HealthTech #IIoT #Mobile #Infographics #smartphones #AI | F93: =LEN(E93)-LEN(SUBSTITUTE(E93,"#","")) -> 11 | G93: 2 hours | H93: 11 | I93: =(H93/D93)*100 -> 0.24466192 | J93: =VALUE(LEFT(G93,SEARCH(" ",G93)-1)) -> 2
A94: 27 | B94: mikequindazzi | C94: 8.5 billion more #smartphones by 2021 will help democratize #AI around the world >> @Qualcomm via @MikeQuindazzi >> #DeepLearning #MachineLearning#ArtificialIntelligence #IoT #BigData#HealthTech #IIoT #Mobile #Infographics >> http://buff.ly/2xcWSLb | D94: 4496 | E94: #DeepLearning #MachineLearning#ArtificialIntelligence #IoT #BigData#HealthTech #IIoT #Mobile #Infographics #smartphones #AI | F94: =LEN(E94)-LEN(SUBSTITUTE(E94,"#","")) -> 11 | G94: 2 hours | H94: 11 | I94: =(H94/D94)*100 -> 0.24466192 | J94: =VALUE(LEFT(G94,SEARCH(" ",G94)-1)) -> 2
A95: 5 | B95: bitcoinebook | C95: Hi #cryptomaniac friend, this is an advice for you! Do you think different? Do you want an example? Explore our BIO 🇬🇧 🇮🇹 Follow me and I return😍 | D95: 2372 | E95: #bitcoinsuperstar #tonylocorriere#blockchain #hodl #hold #market #crypto#now #wallet #product | F95: =LEN(E95)-LEN(SUBSTITUTE(E95,"#","")) -> 10 | G95: 2 hours | H95: 10 | I95: =(H95/D95)*100 -> 0.42158516 | J95: =VALUE(LEFT(G95,SEARCH(" ",G95)-1)) -> 2
... A101: 10 | B101: ricmiqads | C101: One rare and remarkable approach in the overheated #ai market by @ibm | D101: 105 | E101: #ai #artificialintelligence | F101: =LEN(E101)-LEN(SUBSTITUTE(E101,"#","")) -> 2 | G101: 2 hours | H101: 8 | I101: =(H101/D101)*100 -> 7.6190476 | J101: =VALUE(LEFT(G101,SEARCH(" ",G101)-1)) -> 2

Sheet summary
A1: Total Posts | B1: Total Likes | C1: Average Likes | D1: Maximum Likes | E1: Average Followers | F1: Average Like Rate | G1: Average hashtag_count
A2: =COUNTA(sheet1!B:B)-1 -> 100 | B2: =SUM(sheet1!H:H) -> 6333 | C2: =AVERAGE(sheet1!H:H) -> 63.33 | D2: =MAX(sheet1!H:H) -> 358 | E2: =AVERAGE(sheet1!D:D) -> 961.96 | F2: =AVERAGE(sheet1!I:I) -> 15.160028 | G2: =AVERAGE(sheet1!F:F) -> 19.06

Sheet charts
A1: likes | B1: username | D1: Followers | E1: Likes | G1: Hashtag_count | H1: Likes
A2: 349 | B2: astrokpj | D2: 3448 | E2: 349 | G2: =SUM(E2:F2) -> 349 | H2: 349
A3: 350 | B3: gsmusicgroupllc | D3: 226 | E3: 350 | G3: =SUM(E3:F3) -> 350 | H3: 350
A4: 351 | B4: lb3enterprises | D4: 2039 | E4: 351 | G4: =SUM(E4:F4) -> 351 | H4: 351
A5: 352 | B5: superdatascience | D5: 966 | E5: 352 | G5: =SUM(E5:F5) -> 352 | H5: 352
A6: 353 | B6: orcan_intel | D6: 2277 | E6: 353 | G6: =SUM(E6:F6) -> 353 | H6: 353
A7: 354 | B7: theminest_ | D7: 1618 | E7: 354 | G7: =SUM(E7:F7) -> 354 | H7: 354
A8: 355 | B8: mikequindazzi | D8: 1600 | E8: 355 | G8: =SUM(E8:F8) -> 355 | H8: 355
A9: 356 | B9: mikequindazzi | D9: 1600 | E9: 356 | G9: =SUM(E9:F9) -> 356 | H9: 356
A10: 357 | B10: rare.planet | D10: 2573 | E10: 357 | G10: =SUM(E10:F10) -> 357 | H10: 357
A11: 358 | B11: palmariusdev | D11: 741 | E11: 358 | G11: =SUM(E11:F11) -> 358 | H11: 358
D12: 533 | E12: 94 | G12: =SUM(E12:F12) -> 94 | H12: 94
D13: 835 | E13: 93 | G13: =SUM(E13:F13) -> 93 | H13: 93
D14: 828 | E14: 90 | G14: =SUM(E14:F14) -> 90 | H14: 90
D15: 1433 | E15: 86 | G15: =SUM(E15:F15) -> 86 | H15: 86
D16: 914 | E16: 81 | G16: =SUM(E16:F16) -> 81 | H16: 81
D17: 1061 | E17: 80 | G17: =SUM(E17:F17) -> 80 | H17: 80
D18: 2785 | E18: 65 | G18: =SUM(E18:F18) -> 65 | H18: 65
D19: 631 | E19: 55 | G19: =SUM(E19:F19) -> 55 | H19: 55
D20: 971 | E20: 53 | G20: =SUM(E20:F20) -> 53 | H20: 53
D21: 3139 | E21: 51 | G21: =SUM(E21:F21) -> 51 | H21: 51
D22: 383 | E22: 50 | G22: =SUM(E22:F22) -> 50 | H22: 50
D23: 340 | E23: 49 | G23: =SUM(E23:F23) -> 49 | H23: 49
... D76: 371 | E76: 19 | G76: =SUM(E76:F76) -> 19 | H76: 19
D77: 334 | E77: 19 | G77: =SUM(#REF!) -> #REF! | H77: 19
D78: 1231 | E78: 18 | G78: =SUM(E78:F78) -> 18 | H78: 18
D79: 450 | E79: 18 | G79: =SUM(E79:F79) -> 18 | H79: 18
D80: 193 | E80: 18 | G80: =SUM(E80:F80) -> 18 | H80: 18
D81: 530 | E81: 17 | G81: =SUM(E81:F81) -> 17 | H81: 17
D82: 348 | E82: 17 | G82: =SUM(E82:F82) -> 17 | H82: 17
D83: 1196 | E83: 16 | G83: =SUM(E83:F83) -> 16 | H83: 16
D84: 66 | E84: 16 | G84: =SUM(E84:F84) -> 16 | H84: 16
D85: 118 | E85: 16 | G85: =SUM(E85:F85) -> 16 | H85: 16
D86: 145 | E86: 16 | G86: =SUM(E86:F86) -> 16 | H86: 16
D87: 91 | E87: 14 | G87: =SUM(E87:F87) -> 14 | H87: 14
D88: 894 | E88: 14 | G88: =SUM(E88:F88) -> 14 | H88: 14
D89: 1168 | E89: 13 | G89: =SUM(E89:F89) -> 13 | H89: 13
... D101: 105 | E101: 8 | G101: =SUM(E101:F101) -> 8 | H101: 8

Sheet Dashboard
D1: Instagram Engagement Analysis Dashboard
A5: Total Posts | B5: Total Likes | C5: Average Likes | D5: Maximum Likes | E5: Average Followers | F5: Average Like Rate | G5: Average hashtag_count
A6: =COUNTA(sheet1!B:B)-1 -> 100 | B6: =SUM(charts!H:H) -> 6333 | C6: =AVERAGE(charts!H:H) -> 63.33 | D6: =MAX(charts!H:H) -> 358 | E6: =AVERAGE(charts!D:D) -> 961.96 | F6: =AVERAGE(sheet1!I:I) -> 15.160028 | G6: =AVERAGE(sheet1!F:F) -> 19.06
